spip/__init__.py
spip/circular_pixels.py
spip/emm_emirs.py
spip/data/celestial_objects.yml
spip/data/instruments.yml
planetary_spip-1.2.dist-info/LICENSE
planetary_spip-1.2.dist-info/METADATA
planetary_spip-1.2.dist-info/WHEEL
planetary_spip-1.2.dist-info/top_level.txt
planetary_spip-1.2.dist-info/RECORD
