Metadata-Version: 2.1
Name: planetary-spip
Version: 1.2
Summary: Spacecraft Pixel footprint Projection
Author: Aurélien Stcherbinine
Author-email: aurelien.stcherbinine@nau.edu
Project-URL: Source, https://github.com/NAU-PIXEL/spip
Classifier: Programming Language :: Python :: 3
Classifier: License :: OSI Approved :: MIT License
Classifier: Operating System :: OS Independent
Classifier: Intended Audience :: Science/Research
Classifier: Topic :: Scientific/Engineering :: Astronomy
Requires-Python: >=3.6
License-File: LICENSE
Requires-Dist: astropy >=4
Requires-Dist: numpy >=1.19
Requires-Dist: PyYAML >=6
Requires-Dist: tqdm >=4
